{"stats":{"minecraft:custom":{"minecraft:jump":1,"minecraft:time_since_rest":2545,"minecraft:leave_game":1,"minecraft:walk_on_water_one_cm":82,"minecraft:play_time":2545,"minecraft:time_since_death":2545,"minecraft:walk_one_cm":3160,"minecraft:sneak_time":9,"minecraft:total_world_time":3199,"minecraft:fish_caught":2,"minecraft:fly_one_cm":872},"minecraft:used":{"minecraft:farmland":1,"minecraft:wheat_seeds":1,"minecraft:water_bucket":1,"minecraft:fishing_rod":4,"minecraft:bone_meal":2},"minecraft:picked_up":{"minecraft:salmon":2}},"DataVersion":4189}